SEM-2/EE2001-Lab/ramzz/EE2001-master/Exp1001/dff.v
module up_counter(input x,clk,reset,output[1:0] counter);
reg [1:0] counter_up,D,Dprev;
initial D=2'b0;
always @(posedge clk or posedge reset)
begin
Dprev = D;
D[1] = (Dprev[1] & ~x )+(Dprev[0] & x);
D[0] = (Dprev[0] & ~x )+(~Dprev[1] & x); 
if(reset)
 counter_up = 2'b0;
else if(x)
 counter_up = D; 
else
 counter_up = counter_up;
end
assign counter = counter_up;
endmodule

SEM-2/EE2001-Lab/ramzz/EE2001-master/Exp1001/test.v
module upcounter_testbench();
reg clk, reset, x;
wire [1:0] counter;
up_counter dut(x, clk, reset, counter);
initial begin
$dumpfile("test_add.vcd");
$dumpvars(0,upcounter_testbench);
x = 0;
clk=0;
reset = 0;
$monitor( "At t=%t, output=%b,x = %b , reset = %b" , $time ,counter,x,reset);
end
always #5 clk = ~clk;
initial begin
x=1;
reset=1;
#10;reset=0;
#10;x=0;
#10;x=1;
#10;x=0;
#10;x=1;
#80;x=0;
$finish;
end
endmodule

SEM-2/EE2001-Lab/ramzz/EE2001-master/Exp1001/test_add.vcd
$date
	Tue Mar 26 15:39:51 2019
$end
$version
	Icarus Verilog
$end
$timescale
	1s
$end
$scope module upcounter_testbench $end
$var wire 2 ! counter [1:0] $end
$var reg 1 " clk $end
$var reg 1 # reset $end
$var reg 1 $ x $end
$scope module dut $end
$var wire 1 % clk $end
$var wire 2 & counter [1:0] $end
$var wire 1 ' reset $end
$var wire 1 ( x $end
$var reg 2 ) D [1:0] $end
$var reg 2 * Dprev [1:0] $end
$var reg 2 + counter_up [1:0] $end
$upscope $end
$upscope $end
$enddefinitions $end
#0
$dumpvars
b0 +
b0 *
b1 )
1(
1'
b0 &
0%
1$
1#
0"
b0 !
$end
#5
b11 )
b1 *
1"
1%
#10
0"
0%
0#
0'
#15
b10 +
b10 !
b10 &
b10 )
b11 *
1"
1%
#20
0"
0%
0$
0(
#25
b10 )
b10 *
1"
1%
#30
0"
0%
1$
1(
#35
b0 +
b0 !
b0 &
b0 )
1"
1%
#40
0"
0%
0$
0(
#45
b0 )
b0 *
1"
1%
#50
0"
0%
1$
1(
#55
b1 +
b1 !
b1 &
b1 )
1"
1%
#60
0"
0%
#65
b11 +
b11 !
b11 &
b11 )
b1 *
1"
1%
#70
0"
0%
#75
b10 +
b10 !
b10 &
b10 )
b11 *
1"
1%
#80
0"
0%
#85
b0 +
b0 !
b0 &
b0 )
b10 *
1"
1%
#90
0"
0%
#95
b1 +
b1 !
b1 &
b1 )
b0 *
1"
1%
#100
0"
0%
#105
b11 +
b11 !
b11 &
b11 )
b1 *
1"
1%
#110
0"
0%
#115
b10 +
b10 !
b10 &
b10 )
b11 *
1"
1%
#120
0"
0%
#125
b0 +
b0 !
b0 &
b0 )
b10 *
1"
1%
#130
0"
0%
0$
0(
