SEM-2/EE2001-Lab/ramzz/EE2001-master/Exp10/T1/exp.v
module fa_gate(a , b , carryin , sum , carryout);

input a,b,carryin;
output sum,carryout;
wire w1,w2,w3;

xor x1 ( w1 , a ,b ) ;
and a1 ( w2 , a , b ) ;
xor x2 ( sum , carryin , w1 );
and a2 ( w3 , w1 , carryin );
or  o3 ( carryout , w2 ,w3 );

endmodule

SEM-2/EE2001-Lab/ramzz/EE2001-master/Exp10/T1/modules.v
module fa_data(a , b , carryin , sum , carryout);

input a,b,carryin;
output sum,carryout;
wire w1,w2,w3;

assign w1 = a ^ b;
assign w2 = a & b;
assign sum = carryin ^ w1;
assign w3 = w1 & carryin;
assign carryout = w2 + w3;

endmodule

SEM-2/EE2001-Lab/ramzz/EE2001-master/Exp10/T1/testbench.v
module test_fa;
wire s1,s2,cout1,cout2;
reg a,b,c;
fa_data DUT(a,b,c,s1,cout1);
fa_gate DUT1(a,b,c,s2,cout2);
initial
begin
$dumpfile("testfadd.vcd");
$dumpvars(0,test_fa);
$monitor("At time = %t , a = %b , b = %b , Carry in = %b, s_data = %b , cout_data = %b , s_gate = %b , cout_gate = %b",$time,a,b,c,s1,cout1,s2,cout2);
#10 a = 0; b = 0; c = 0;
#10 a = 0; b = 0; c = 1;
#10 a = 0; b = 1; c = 0;
#10 a = 0; b = 1; c = 1;
#10 a = 1; b = 0; c = 0;
#10 a = 1; b = 0; c = 1;
#10 a = 1; b = 1; c = 0;
#10 a = 1; b = 1; c = 1;
#10 $finish;
end
endmodule

SEM-2/EE2001-Lab/ramzz/EE2001-master/Exp10/T1/testfadd.vcd
$date
	Tue Jan 29 16:04:50 2019
$end
$version
	Icarus Verilog
$end
$timescale
	1s
$end
$scope module test_fa $end
$var wire 1 ! s2 $end
$var wire 1 " s1 $end
$var wire 1 # cout2 $end
$var wire 1 $ cout1 $end
$var reg 1 % a $end
$var reg 1 & b $end
$var reg 1 ' c $end
$scope module DUT $end
$var wire 1 % a $end
$var wire 1 & b $end
$var wire 1 ' carryin $end
$var wire 1 " sum $end
$var wire 1 ( w1 $end
$var wire 1 ) w2 $end
$var wire 1 * w3 $end
$var wire 1 $ carryout $end
$upscope $end
$scope module DUT1 $end
$var wire 1 % a $end
$var wire 1 & b $end
$var wire 1 ' carryin $end
$var wire 1 # carryout $end
$var wire 1 ! sum $end
$var wire 1 + w1 $end
$var wire 1 , w2 $end
$var wire 1 - w3 $end
$upscope $end
$upscope $end
$enddefinitions $end
#0
$dumpvars
x-
x,
x+
x*
x)
x(
x'
x&
x%
x$
x#
x"
x!
$end
#10
0#
0"
0$
0*
0!
0-
0(
0)
0+
0,
0'
0&
0%
#20
1"
1!
1'
#30
1(
1+
0'
1&
#40
1#
0"
1$
1*
0!
1-
1'
#50
0#
1"
0$
0*
1!
0-
0'
0&
1%
#60
1#
0"
1$
1*
0!
1-
1'
#70
0*
0-
0(
1$
1)
0+
1,
0'
1&
#80
1"
1!
1'
